indian_repair/__init__.py
indian_repair/cli.py
indian_repair/os_restart.py
indian_repair-1.1.dist-info/LICENSE
indian_repair-1.1.dist-info/METADATA
indian_repair-1.1.dist-info/WHEEL
indian_repair-1.1.dist-info/entry_points.txt
indian_repair-1.1.dist-info/top_level.txt
indian_repair-1.1.dist-info/RECORD
