Metadata-Version: 2.1
Name: indian-repair
Version: 1.1
Summary: Crazy Tool that can fix your network, storage, lag or any effin issue that you have no idea about. Just run indian-repair and see the magic.
Home-page: https://github.com/sickuritywizard/indian-repair
Author: Pradeep Kumar N
Author-email: prajeet67@gmail.com
Classifier: Programming Language :: Python :: 3
Classifier: License :: OSI Approved :: MIT License
Classifier: Operating System :: OS Independent
Requires-Python: >=3.6
License-File: LICENSE
Requires-Dist: click
